explainy/__init__.py
explainy/core/__init__.py
explainy/core/explanation.py
explainy/core/explanation_base.py
explainy/explanations/__init__.py
explainy/explanations/counterfactual_explanation.py
explainy/explanations/permutation_explanation.py
explainy/explanations/shap_explanation.py
explainy/explanations/surrogate_model_explanation.py
explainy/utils/__init__.py
explainy/utils/logger.py
explainy/utils/surrogate_plot.py
explainy/utils/surrogate_text.py
explainy/utils/typing.py
explainy/utils/utils.py
explainy-0.2.12.dist-info/LICENSE
explainy-0.2.12.dist-info/METADATA
explainy-0.2.12.dist-info/WHEEL
explainy-0.2.12.dist-info/entry_points.txt
explainy-0.2.12.dist-info/top_level.txt
explainy-0.2.12.dist-info/RECORD
