Metadata-Version: 2.1
Name: explainy
Version: 0.2.12
Summary: explainy is a library for generating explanations for machine learning models in Python. It uses methods from Machine Learning Explainability and provides a standardized API to create feature importance explanations for samples. The explanations are generated in the form of plots and text.
Home-page: https://github.com/MauroLuzzatto/explainy
Author: Mauro Luzzatto
Author-email: mauroluzzatto@hotmail.com
License: MIT license
Keywords: explainy
Classifier: Development Status :: 2 - Pre-Alpha
Classifier: Intended Audience :: Developers
Classifier: License :: OSI Approved :: MIT License
Classifier: Natural Language :: English
Classifier: Programming Language :: Python :: 3
Classifier: Programming Language :: Python :: 3.9
Classifier: Programming Language :: Python :: 3.10
Classifier: Programming Language :: Python :: 3.11
Requires-Python: >=3.9
License-File: LICENSE
Requires-Dist: scikit-learn ==1.5.0
Requires-Dist: pandas
Requires-Dist: mlxtend ==0.23.0
Requires-Dist: shap ==0.44.0
Requires-Dist: matplotlib ==3.7.1
Requires-Dist: graphviz ==0.16
Requires-Dist: numpy ==1.23.1
Requires-Dist: matplotlib-inline ==0.1.2
Requires-Dist: ipykernel
Requires-Dist: ipython
Requires-Dist: ipywidgets
